pyimporter/__init__.py
pyimporter/common.py
pyimporter/finder.py
pyimporter/importer.py
pyimporter/loader.py
tests/__init__.py
tests/conftest.py
tests/test_url_import.py
pyimporter-0.0.2.dist-info/METADATA
pyimporter-0.0.2.dist-info/WHEEL
pyimporter-0.0.2.dist-info/top_level.txt
pyimporter-0.0.2.dist-info/RECORD
