Metadata-Version: 2.1
Name: pyimporter
Version: 0.0.2
Summary: Python import library extensions with implementation to import from url.
Home-page: https://github.com/ivangeorgiev/gems/tree/master/src/python-import-from-url/
Author: Example Author
Author-email: author@example.com
License: UNKNOWN
Platform: UNKNOWN
Classifier: Programming Language :: Python :: 3
Classifier: License :: OSI Approved :: MIT License
Classifier: Operating System :: OS Independent
Requires-Python: >=3.6
